[
  {
    "department": "PSYCAP",
    "number": "514CHILD",
    "title": "/AD PSYCHPATHGY",
    "sections": [
      {
        "sln": "",
        "section_id": "",
        "times": "",
        "building": "",
        "room": "",
        "instructor": "",
        "status": "Open",
        "additional_info": []
      }
    ]
  },
  {
    "department": "PSYCAP",
    "number": "524EBP CBT",
    "title": "ANX MOOD",
    "sections": [
      {
        "sln": "",
        "section_id": "",
        "times": "",
        "building": "",
        "room": "",
        "instructor": "",
        "status": "",
        "additional_info": []
      },
      {
        "sln": "",
        "section_id": "",
        "times": "",
        "building": "",
        "room": "",
        "instructor": "",
        "status": "",
        "additional_info": []
      }
    ]
  },
  {
    "department": "PSYCAP",
    "number": "526EBP PARENTIN",
    "title": "G",
    "sections": [
      {
        "sln": "",
        "section_id": "",
        "times": "",
        "building": "MW",
        "room": "400",
        "instructor": "",
        "status": "Open",
        "additional_info": []
      }
    ]
  },
  {
    "department": "PSYCAP",
    "number": "528MULTCULTR COUNSL",
    "title": "STG",
    "sections": [
      {
        "sln": "",
        "section_id": "",
        "times": "",
        "building": "FOR",
        "room": "2",
        "instructor": "",
        "status": "",
        "additional_info": []
      },
      {
        "sln": "",
        "section_id": "",
        "times": "",
        "building": "FOR",
        "room": "2",
        "instructor": "",
        "status": "",
        "additional_info": []
      },
      {
        "sln": "",
        "section_id": "",
        "times": "",
        "building": "",
        "room": "",
        "instructor": "",
        "status": "",
        "additional_info": []
      },
      {
        "sln": "",
        "section_id": "",
        "times": "",
        "building": "",
        "room": "",
        "instructor": "",
        "status": "",
        "additional_info": []
      }
    ]
  },
  {
    "department": "PSYCAP",
    "number": "560APPLD PRACTICU",
    "title": "M",
    "sections": [
      {
        "sln": "",
        "section_id": "",
        "times": "",
        "building": "",
        "room": "",
        "instructor": "",
        "status": "",
        "additional_info": []
      },
      {
        "sln": "",
        "section_id": "",
        "times": "",
        "building": "",
        "room": "",
        "instructor": "",
        "status": "",
        "additional_info": []
      }
    ]
  }
]