[
  {
    "department": "ENV H",
    "number": "105ENVHLTH ACAD",
    "title": "SKILLS",
    "sections": [
      {
        "sln": "",
        "section_id": "",
        "times": "",
        "building": "ICT",
        "room": "226",
        "instructor": "",
        "status": "Open",
        "additional_info": []
      }
    ]
  },
  {
    "department": "ENV H",
    "number": "111ENVR HLTH",
    "title": "CONNECTS",
    "sections": [
      {
        "sln": "",
        "section_id": "",
        "times": "TTh    1030-1150",
        "building": "",
        "room": "",
        "instructor": "",
        "status": "Open",
        "additional_info": []
      }
    ]
  },
  {
    "department": "ENV H",
    "number": "205ENVIR HLTH",
    "title": "MEDIA",
    "sections": [
      {
        "sln": "",
        "section_id": "",
        "times": "",
        "building": "",
        "room": "",
        "instructor": "",
        "status": "Open",
        "additional_info": []
      }
    ]
  },
  {
    "department": "ENV H",
    "number": "311INTRO TO",
    "title": "ENV HEALTH",
    "sections": [
      {
        "sln": "",
        "section_id": "",
        "times": "",
        "building": "MWF",
        "room": "1030",
        "instructor": "",
        "status": "Open",
        "additional_info": []
      }
    ]
  },
  {
    "department": "ENV H",
    "number": "405TOXICS",
    "title": "& HUMAN HLTH",
    "sections": [
      {
        "sln": "",
        "section_id": "",
        "times": "",
        "building": "MWF",
        "room": "130",
        "instructor": "",
        "status": "Open",
        "additional_info": []
      }
    ]
  },
  {
    "department": "ENV H",
    "number": "409MICROBIOME",
    "title": "&ENV HLTH",
    "sections": [
      {
        "sln": "",
        "section_id": "",
        "times": "",
        "building": "",
        "room": "",
        "instructor": "",
        "status": "Open",
        "additional_info": []
      }
    ]
  },
  {
    "department": "ENV H",
    "number": "417CHILD ENV",
    "title": "HLTH DISP",
    "sections": [
      {
        "sln": "",
        "section_id": "",
        "times": "",
        "building": "",
        "room": "",
        "instructor": "",
        "status": "Open",
        "additional_info": []
      }
    ]
  },
  {
    "department": "ENV H",
    "number": "428LEADERSHIP IN",
    "title": "PH III",
    "sections": [
      {
        "sln": "",
        "section_id": "",
        "times": "",
        "building": "TO",
        "room": "6",
        "instructor": "",
        "status": "",
        "additional_info": []
      }
    ]
  },
  {
    "department": "ENV H",
    "number": "432CHEM SAMP",
    "title": "& ANALYSIS",
    "sections": [
      {
        "sln": "",
        "section_id": "",
        "times": "",
        "building": "MW",
        "room": "830",
        "instructor": "",
        "status": "Closed",
        "additional_info": []
      }
    ]
  },
  {
    "department": "ENV H",
    "number": "442ZOONOTIC DISEAS",
    "title": "E",
    "sections": [
      {
        "sln": "",
        "section_id": "",
        "times": "",
        "building": "WF",
        "room": "230",
        "instructor": "",
        "status": "Open",
        "additional_info": []
      }
    ]
  },
  {
    "department": "ENV H",
    "number": "447ENV CHG",
    "title": "INF DISEASE",
    "sections": [
      {
        "sln": "",
        "section_id": "",
        "times": "",
        "building": "ARE",
        "room": "2",
        "instructor": "SECTIONS OF THISCOURSE:ENV H 447 AND ENV H 547THERE IS AN OVERALL LIMIT FOR THE 2SECTIONS COMBINED.STUDENTS CANREGISTER UNDER EITHERSECTION UNTIL THE LIMIT IS REACHED.AS LONG AS THE \"STATUS\" FIELD IS\"OPEN\", STUDENTS CAN REGISTERWITHOUT AN ENTRY CODE.",
        "status": "Open",
        "additional_info": []
      }
    ]
  },
  {
    "department": "ENV H",
    "number": "452CONTRL ENV",
    "title": "MICR HAZ",
    "sections": [
      {
        "sln": "",
        "section_id": "",
        "times": "",
        "building": "MWF",
        "room": "1130",
        "instructor": "",
        "status": "Open",
        "additional_info": []
      }
    ]
  },
  {
    "department": "ENV H",
    "number": "462TECH ASP",
    "title": "OCC SAFETY",
    "sections": [
      {
        "sln": "",
        "section_id": "",
        "times": "",
        "building": "MW",
        "room": "100",
        "instructor": "",
        "status": "Closed",
        "additional_info": []
      }
    ]
  },
  {
    "department": "ENV H",
    "number": "475ENV JUSTICE",
    "title": "POP HLTH",
    "sections": [
      {
        "sln": "",
        "section_id": "",
        "times": "",
        "building": "",
        "room": "",
        "instructor": "",
        "status": "Open",
        "additional_info": []
      }
    ]
  },
  {
    "department": "ENV H",
    "number": "479CLIMATE CHNG",
    "title": "PH PRAC",
    "sections": [
      {
        "sln": "",
        "section_id": "",
        "times": "",
        "building": "MW",
        "room": "330",
        "instructor": "",
        "status": "Open",
        "additional_info": []
      }
    ]
  },
  {
    "department": "ENV H",
    "number": "480UG SEMINA",
    "title": "R",
    "sections": [
      {
        "sln": "",
        "section_id": "",
        "times": "",
        "building": "",
        "room": "",
        "instructor": "",
        "status": "",
        "additional_info": []
      }
    ]
  },
  {
    "department": "ENV H",
    "number": "482EH INTERNSHI",
    "title": "P",
    "sections": [
      {
        "sln": "",
        "section_id": "",
        "times": "",
        "building": "",
        "room": "",
        "instructor": "",
        "status": "",
        "additional_info": []
      }
    ]
  },
  {
    "department": "ENV H",
    "number": "497ENVH SPEC",
    "title": "ELECTVS",
    "sections": [
      {
        "sln": "",
        "section_id": "",
        "times": "",
        "building": "",
        "room": "",
        "instructor": "",
        "status": "",
        "additional_info": []
      }
    ]
  },
  {
    "department": "ENV H",
    "number": "499UNDERGRAD RESEARC",
    "title": "H",
    "sections": [
      {
        "sln": "",
        "section_id": "",
        "times": "",
        "building": "",
        "room": "",
        "instructor": "",
        "status": "",
        "additional_info": []
      },
      {
        "sln": "",
        "section_id": "",
        "times": "",
        "building": "",
        "room": "",
        "instructor": "",
        "status": "",
        "additional_info": []
      }
    ]
  },
  {
    "department": "ENV H",
    "number": "504ADV EHS",
    "title": "RES METHODS",
    "sections": [
      {
        "sln": "",
        "section_id": "",
        "times": "",
        "building": "",
        "room": "",
        "instructor": "",
        "status": "Open",
        "additional_info": []
      }
    ]
  },
  {
    "department": "ENV H",
    "number": "509MICROBIOME",
    "title": "&ENV HLTH",
    "sections": [
      {
        "sln": "",
        "section_id": "",
        "times": "",
        "building": "",
        "room": "",
        "instructor": "",
        "status": "Open",
        "additional_info": []
      }
    ]
  },
  {
    "department": "ENV H",
    "number": "516TOXIC AGENT",
    "title": "S",
    "sections": [
      {
        "sln": "",
        "section_id": "",
        "times": "",
        "building": "MW",
        "room": "830",
        "instructor": "",
        "status": "Open",
        "additional_info": []
      }
    ]
  },
  {
    "department": "ENV H",
    "number": "528LEADERSHIP IN",
    "title": "PH III",
    "sections": [
      {
        "sln": "",
        "section_id": "",
        "times": "",
        "building": "TO",
        "room": "6",
        "instructor": "",
        "status": "",
        "additional_info": []
      }
    ]
  },
  {
    "department": "ENV H",
    "number": "536HLTH IMPACT",
    "title": "ASSESS",
    "sections": [
      {
        "sln": "",
        "section_id": "",
        "times": "",
        "building": "",
        "room": "",
        "instructor": "",
        "status": "Open",
        "additional_info": []
      }
    ]
  },
  {
    "department": "ENV H",
    "number": "537DATA SCIENCE",
    "title": "INTGRTY",
    "sections": [
      {
        "sln": "",
        "section_id": "",
        "times": "",
        "building": "",
        "room": "",
        "instructor": "",
        "status": "Open",
        "additional_info": []
      }
    ]
  },
  {
    "department": "ENV H",
    "number": "547ENV CHG",
    "title": "INF DISEASE",
    "sections": [
      {
        "sln": "",
        "section_id": "",
        "times": "",
        "building": "ARE",
        "room": "2",
        "instructor": "SECTIONS OF THISCOURSE:ENV H 447 AND ENV H 547THERE IS AN OVERALL LIMIT FOR THE 2SECTIONS COMBINED.STUDENTS CANREGISTER UNDER EITHERSECTION UNTIL THE LIMIT IS REACHED.AS LONG AS THE \"STATUS\" FIELD IS\"OPEN\", STUDENTS CAN REGISTERWITHOUT AN ENTRY CODE.",
        "status": "Open",
        "additional_info": []
      }
    ]
  },
  {
    "department": "ENV H",
    "number": "550OCC ENV",
    "title": "DISEASE",
    "sections": [
      {
        "sln": "",
        "section_id": "",
        "times": "",
        "building": "",
        "room": "",
        "instructor": "",
        "status": "Closed",
        "additional_info": []
      },
      {
        "sln": "",
        "section_id": "",
        "times": "",
        "building": "",
        "room": "",
        "instructor": "",
        "status": "Closed",
        "additional_info": []
      }
    ]
  },
  {
    "department": "ENV H",
    "number": "552CONTRL ENV",
    "title": "MICR HAZ",
    "sections": [
      {
        "sln": "",
        "section_id": "",
        "times": "",
        "building": "MWF",
        "room": "1130",
        "instructor": "",
        "status": "Open",
        "additional_info": []
      }
    ]
  },
  {
    "department": "ENV H",
    "number": "555IND HYG",
    "title": "METHODS LAB",
    "sections": [
      {
        "sln": "",
        "section_id": "",
        "times": "",
        "building": "MW",
        "room": "830",
        "instructor": "",
        "status": "Open",
        "additional_info": []
      }
    ]
  },
  {
    "department": "ENV H",
    "number": "562TECH ASP",
    "title": "OCC SAFETY",
    "sections": [
      {
        "sln": "",
        "section_id": "",
        "times": "",
        "building": "MW",
        "room": "100",
        "instructor": "",
        "status": "Closed",
        "additional_info": []
      }
    ]
  },
  {
    "department": "ENV H",
    "number": "563HLTH",
    "title": "& SAF PHYS AGNT",
    "sections": [
      {
        "sln": "",
        "section_id": "",
        "times": "",
        "building": "MW",
        "room": "230",
        "instructor": "",
        "status": "Open",
        "additional_info": []
      }
    ]
  },
  {
    "department": "ENV H",
    "number": "570ENVIR",
    "title": "& OCCUP EPIDM",
    "sections": [
      {
        "sln": "",
        "section_id": "",
        "times": "",
        "building": "MW",
        "room": "330",
        "instructor": "",
        "status": "Open",
        "additional_info": []
      }
    ]
  },
  {
    "department": "ENV H",
    "number": "575ENV JUSTICE",
    "title": "POP HLTH",
    "sections": [
      {
        "sln": "",
        "section_id": "",
        "times": "",
        "building": "",
        "room": "",
        "instructor": "",
        "status": "Open",
        "additional_info": []
      }
    ]
  },
  {
    "department": "ENV H",
    "number": "579CLIMATE CHNG",
    "title": "PH PRAC",
    "sections": [
      {
        "sln": "",
        "section_id": "",
        "times": "",
        "building": "MW",
        "room": "330",
        "instructor": "",
        "status": "Open",
        "additional_info": []
      }
    ]
  },
  {
    "department": "ENV H",
    "number": "580ENV",
    "title": "/OCC HLTH SEMINAR",
    "sections": [
      {
        "sln": "",
        "section_id": "",
        "times": "",
        "building": "",
        "room": "",
        "instructor": "",
        "status": "Open",
        "additional_info": []
      }
    ]
  },
  {
    "department": "ENV H",
    "number": "583THESIS PROPSL",
    "title": "PREP",
    "sections": [
      {
        "sln": "",
        "section_id": "",
        "times": "",
        "building": "",
        "room": "",
        "instructor": "",
        "status": "Open",
        "additional_info": []
      }
    ]
  },
  {
    "department": "ENV H",
    "number": "590SELECTED TOPIC",
    "title": "S",
    "sections": [
      {
        "sln": "",
        "section_id": "",
        "times": "",
        "building": "WF",
        "room": "130",
        "instructor": "",
        "status": "Open",
        "additional_info": []
      }
    ]
  },
  {
    "department": "ENV H",
    "number": "593CURRENT TOPICS",
    "title": "-RISK",
    "sections": [
      {
        "sln": "",
        "section_id": "",
        "times": "",
        "building": "",
        "room": "",
        "instructor": "",
        "status": "Open",
        "additional_info": []
      }
    ]
  },
  {
    "department": "ENV H",
    "number": "595RESEARCH ROTATIO",
    "title": "N",
    "sections": [
      {
        "sln": "",
        "section_id": "",
        "times": "",
        "building": "",
        "room": "",
        "instructor": "",
        "status": "",
        "additional_info": []
      }
    ]
  },
  {
    "department": "ENV H",
    "number": "596ISS OCCPTNL",
    "title": "/ENV MED",
    "sections": [
      {
        "sln": "",
        "section_id": "",
        "times": "",
        "building": "FOR",
        "room": "4",
        "instructor": "TOTAL CREDITS.(SYNCHRONOUS INSTRUCTION)",
        "status": "Open",
        "additional_info": []
      }
    ]
  },
  {
    "department": "ENV H",
    "number": "597CASES ENVH",
    "title": "OCC HLTH",
    "sections": [
      {
        "sln": "",
        "section_id": "",
        "times": "",
        "building": "",
        "room": "",
        "instructor": "",
        "status": "Open",
        "additional_info": []
      }
    ]
  },
  {
    "department": "ENV H",
    "number": "598PROJECT",
    "title": "/PORTFOLIO",
    "sections": [
      {
        "sln": "",
        "section_id": "",
        "times": "",
        "building": "",
        "room": "",
        "instructor": "",
        "status": "",
        "additional_info": []
      },
      {
        "sln": "",
        "section_id": "",
        "times": "",
        "building": "",
        "room": "",
        "instructor": "",
        "status": "Open",
        "additional_info": []
      }
    ]
  },
  {
    "department": "ENV H",
    "number": "599FIELD STUDIE",
    "title": "S",
    "sections": [
      {
        "sln": "",
        "section_id": "",
        "times": "",
        "building": "",
        "room": "",
        "instructor": "",
        "status": "",
        "additional_info": []
      },
      {
        "sln": "",
        "section_id": "",
        "times": "",
        "building": "",
        "room": "",
        "instructor": "",
        "status": "",
        "additional_info": []
      }
    ]
  },
  {
    "department": "ENV H",
    "number": "600INDEPNDNT STDY",
    "title": "/RSCH",
    "sections": [
      {
        "sln": "",
        "section_id": "",
        "times": "",
        "building": "",
        "room": "",
        "instructor": "",
        "status": "",
        "additional_info": []
      },
      {
        "sln": "",
        "section_id": "",
        "times": "",
        "building": "",
        "room": "",
        "instructor": "",
        "status": "",
        "additional_info": []
      }
    ]
  },
  {
    "department": "ENV H",
    "number": "700MASTERS THESI",
    "title": "S",
    "sections": [
      {
        "sln": "",
        "section_id": "",
        "times": "",
        "building": "",
        "room": "",
        "instructor": "",
        "status": "",
        "additional_info": []
      }
    ]
  },
  {
    "department": "ENV H",
    "number": "800DOCTORAL DISSERTAT",
    "title": "N",
    "sections": [
      {
        "sln": "",
        "section_id": "",
        "times": "",
        "building": "",
        "room": "",
        "instructor": "",
        "status": "",
        "additional_info": []
      }
    ]
  }
]