[
  {
    "department": "CHSTU",
    "number": "200LATINOS IN",
    "title": "THE US",
    "sections": [
      {
        "sln": "",
        "section_id": "",
        "times": "",
        "building": "MW",
        "room": "230",
        "instructor": "",
        "status": "Open",
        "additional_info": []
      }
    ]
  },
  {
    "department": "CHSTU",
    "number": "260INTRO CHICANO",
    "title": "POLIT",
    "sections": [
      {
        "sln": "",
        "section_id": "",
        "times": "",
        "building": "",
        "room": "",
        "instructor": "",
        "status": "Open",
        "additional_info": []
      }
    ]
  },
  {
    "department": "CHSTU",
    "number": "320FOOD SOVEREIGNT",
    "title": "Y",
    "sections": [
      {
        "sln": "",
        "section_id": "",
        "times": "TTh    130-320",
        "building": "",
        "room": "",
        "instructor": "",
        "status": "Open",
        "additional_info": []
      }
    ]
  },
  {
    "department": "CHSTU",
    "number": "342WORKING LATINAS",
    "title": "/OS",
    "sections": [
      {
        "sln": "",
        "section_id": "",
        "times": "",
        "building": "MW",
        "room": "1030",
        "instructor": "",
        "status": "Open",
        "additional_info": []
      }
    ]
  },
  {
    "department": "CHSTU",
    "number": "499IND STUDY",
    "title": "& RESEARCH",
    "sections": [
      {
        "sln": "",
        "section_id": "",
        "times": "",
        "building": "",
        "room": "",
        "instructor": "",
        "status": "",
        "additional_info": []
      }
    ]
  }
]