[
  {
    "department": "MARBIO",
    "number": "270AQUATIC ECOPHYSLG",
    "title": "Y",
    "sections": [
      {
        "sln": "",
        "section_id": "",
        "times": "",
        "building": "MWF",
        "room": "930",
        "instructor": "",
        "status": "Open",
        "additional_info": []
      },
      {
        "sln": "",
        "section_id": "",
        "times": "",
        "building": "",
        "room": "",
        "instructor": "",
        "status": "Closed",
        "additional_info": []
      },
      {
        "sln": "",
        "section_id": "",
        "times": "",
        "building": "",
        "room": "",
        "instructor": "",
        "status": "Open",
        "additional_info": []
      },
      {
        "sln": "",
        "section_id": "",
        "times": "",
        "building": "",
        "room": "",
        "instructor": "",
        "status": "Open",
        "additional_info": []
      }
    ]
  },
  {
    "department": "MARBIO",
    "number": "301CURRENT TPCS",
    "title": "MAR BIO",
    "sections": [
      {
        "sln": "",
        "section_id": "",
        "times": "",
        "building": "",
        "room": "",
        "instructor": "",
        "status": "Open",
        "additional_info": []
      }
    ]
  },
  {
    "department": "MARBIO",
    "number": "305MARINE SCI",
    "title": "WRIT",
    "sections": [
      {
        "sln": "",
        "section_id": "",
        "times": "",
        "building": "MW",
        "room": "330",
        "instructor": "",
        "status": "Open",
        "additional_info": []
      }
    ]
  },
  {
    "department": "MARBIO",
    "number": "479MARINE BIO",
    "title": "RESEARCH",
    "sections": [
      {
        "sln": "",
        "section_id": "",
        "times": "",
        "building": "",
        "room": "",
        "instructor": "",
        "status": "",
        "additional_info": []
      }
    ]
  }
]