[
  {
    "department": "A A",
    "number": "101AIR",
    "title": "/SPACE VEHICLES",
    "sections": [
      {
        "sln": "",
        "section_id": "",
        "times": "MTWF   130-220",
        "building": "MTWF",
        "room": "130",
        "instructor": "",
        "status": "Open",
        "additional_info": []
      },
      {
        "sln": "",
        "section_id": "",
        "times": "",
        "building": "",
        "room": "",
        "instructor": "",
        "status": "Open",
        "additional_info": []
      },
      {
        "sln": "",
        "section_id": "",
        "times": "",
        "building": "",
        "room": "",
        "instructor": "",
        "status": "Open",
        "additional_info": []
      },
      {
        "sln": "",
        "section_id": "",
        "times": "",
        "building": "",
        "room": "",
        "instructor": "",
        "status": "Open",
        "additional_info": []
      }
    ]
  },
  {
    "department": "A A",
    "number": "210ENGR STATIC",
    "title": "S",
    "sections": [
      {
        "sln": "",
        "section_id": "",
        "times": "",
        "building": "MWF",
        "room": "1030",
        "instructor": "",
        "status": "Open",
        "additional_info": []
      },
      {
        "sln": "",
        "section_id": "",
        "times": "",
        "building": "",
        "room": "",
        "instructor": "",
        "status": "Open",
        "additional_info": []
      },
      {
        "sln": "",
        "section_id": "",
        "times": "",
        "building": "",
        "room": "",
        "instructor": "",
        "status": "Open",
        "additional_info": []
      },
      {
        "sln": "",
        "section_id": "",
        "times": "",
        "building": "",
        "room": "",
        "instructor": "",
        "status": "Open",
        "additional_info": []
      },
      {
        "sln": "",
        "section_id": "",
        "times": "",
        "building": "",
        "room": "",
        "instructor": "",
        "status": "Open",
        "additional_info": []
      },
      {
        "sln": "",
        "section_id": "",
        "times": "",
        "building": "",
        "room": "",
        "instructor": "",
        "status": "Open",
        "additional_info": []
      },
      {
        "sln": "",
        "section_id": "",
        "times": "",
        "building": "",
        "room": "",
        "instructor": "",
        "status": "Open",
        "additional_info": []
      }
    ]
  },
  {
    "department": "A A",
    "number": "299UNDERGRAD RESEARC",
    "title": "H",
    "sections": [
      {
        "sln": "",
        "section_id": "",
        "times": "",
        "building": "",
        "room": "",
        "instructor": "",
        "status": "",
        "additional_info": []
      },
      {
        "sln": "",
        "section_id": "",
        "times": "",
        "building": "",
        "room": "",
        "instructor": "",
        "status": "",
        "additional_info": []
      },
      {
        "sln": "",
        "section_id": "",
        "times": "",
        "building": "",
        "room": "",
        "instructor": "",
        "status": "",
        "additional_info": []
      },
      {
        "sln": "",
        "section_id": "",
        "times": "",
        "building": "",
        "room": "",
        "instructor": "",
        "status": "",
        "additional_info": []
      },
      {
        "sln": "",
        "section_id": "",
        "times": "",
        "building": "",
        "room": "",
        "instructor": "",
        "status": "",
        "additional_info": []
      }
    ]
  },
  {
    "department": "A A",
    "number": "302INCOMP AERODYNAMIC",
    "title": "S",
    "sections": [
      {
        "sln": "",
        "section_id": "",
        "times": "",
        "building": "",
        "room": "",
        "instructor": "",
        "status": "Open",
        "additional_info": []
      }
    ]
  },
  {
    "department": "A A",
    "number": "312STRUCT VIBRATION",
    "title": "S",
    "sections": [
      {
        "sln": "",
        "section_id": "",
        "times": "",
        "building": "WF",
        "room": "1030",
        "instructor": "",
        "status": "Open",
        "additional_info": []
      }
    ]
  },
  {
    "department": "A A",
    "number": "321AEROSPACE LAB",
    "title": "I",
    "sections": [
      {
        "sln": "",
        "section_id": "",
        "times": "",
        "building": "",
        "room": "",
        "instructor": "",
        "status": "Open",
        "additional_info": []
      },
      {
        "sln": "",
        "section_id": "",
        "times": "T      1130-120",
        "building": "AERB",
        "room": "117",
        "instructor": "",
        "status": "Closed",
        "additional_info": []
      },
      {
        "sln": "",
        "section_id": "",
        "times": "T      130-320",
        "building": "AERB",
        "room": "117",
        "instructor": "",
        "status": "Open",
        "additional_info": []
      },
      {
        "sln": "",
        "section_id": "",
        "times": "Th     1030-1220",
        "building": "AERB",
        "room": "117",
        "instructor": "",
        "status": "Closed",
        "additional_info": []
      },
      {
        "sln": "",
        "section_id": "",
        "times": "Th     1230-220",
        "building": "AERB",
        "room": "117",
        "instructor": "",
        "status": "Closed",
        "additional_info": []
      },
      {
        "sln": "",
        "section_id": "",
        "times": "Th     230-420",
        "building": "AERB",
        "room": "117",
        "instructor": "",
        "status": "Open",
        "additional_info": []
      }
    ]
  },
  {
    "department": "A A",
    "number": "331AEROSPACE STRUCT",
    "title": "I",
    "sections": [
      {
        "sln": "",
        "section_id": "",
        "times": "",
        "building": "WF",
        "room": "130",
        "instructor": "",
        "status": "Open",
        "additional_info": []
      }
    ]
  },
  {
    "department": "A A",
    "number": "410AIRCRAFT DESIGN",
    "title": "I",
    "sections": [
      {
        "sln": "",
        "section_id": "",
        "times": "",
        "building": "NOV",
        "room": "24",
        "instructor": "",
        "status": "",
        "additional_info": []
      },
      {
        "sln": "",
        "section_id": "",
        "times": "",
        "building": "",
        "room": "",
        "instructor": "",
        "status": "",
        "additional_info": []
      },
      {
        "sln": "",
        "section_id": "",
        "times": "",
        "building": "",
        "room": "",
        "instructor": "",
        "status": "",
        "additional_info": []
      },
      {
        "sln": "",
        "section_id": "",
        "times": "",
        "building": "",
        "room": "",
        "instructor": "",
        "status": "",
        "additional_info": []
      },
      {
        "sln": "",
        "section_id": "",
        "times": "",
        "building": "",
        "room": "",
        "instructor": "",
        "status": "",
        "additional_info": []
      },
      {
        "sln": "",
        "section_id": "",
        "times": "",
        "building": "",
        "room": "",
        "instructor": "",
        "status": "",
        "additional_info": []
      },
      {
        "sln": "",
        "section_id": "",
        "times": "",
        "building": "",
        "room": "",
        "instructor": "",
        "status": "",
        "additional_info": []
      }
    ]
  },
  {
    "department": "A A",
    "number": "419AEROSPACE HEAT",
    "title": "TSFR",
    "sections": [
      {
        "sln": "",
        "section_id": "",
        "times": "",
        "building": "",
        "room": "",
        "instructor": "",
        "status": "Open",
        "additional_info": []
      }
    ]
  },
  {
    "department": "A A",
    "number": "420SPACE SYS",
    "title": "DESIGN I",
    "sections": [
      {
        "sln": "",
        "section_id": "",
        "times": "",
        "building": "NOV",
        "room": "24",
        "instructor": "",
        "status": "",
        "additional_info": []
      },
      {
        "sln": "",
        "section_id": "",
        "times": "",
        "building": "",
        "room": "",
        "instructor": "",
        "status": "",
        "additional_info": []
      },
      {
        "sln": "",
        "section_id": "",
        "times": "",
        "building": "",
        "room": "",
        "instructor": "",
        "status": "",
        "additional_info": []
      },
      {
        "sln": "",
        "section_id": "",
        "times": "",
        "building": "",
        "room": "",
        "instructor": "",
        "status": "",
        "additional_info": []
      },
      {
        "sln": "",
        "section_id": "",
        "times": "",
        "building": "",
        "room": "",
        "instructor": "",
        "status": "",
        "additional_info": []
      }
    ]
  },
  {
    "department": "A A",
    "number": "430FINTE ELEMENT",
    "title": "ANALYS",
    "sections": [
      {
        "sln": "",
        "section_id": "",
        "times": "",
        "building": "WF",
        "room": "830",
        "instructor": "",
        "status": "Open",
        "additional_info": []
      }
    ]
  },
  {
    "department": "A A",
    "number": "461AIRBREATH PROP",
    "title": "L",
    "sections": [
      {
        "sln": "",
        "section_id": "",
        "times": "",
        "building": "WF",
        "room": "1130",
        "instructor": "",
        "status": "Open",
        "additional_info": []
      }
    ]
  },
  {
    "department": "A A",
    "number": "462ROCKET PROPULSIO",
    "title": "N",
    "sections": [
      {
        "sln": "",
        "section_id": "",
        "times": "",
        "building": "WF",
        "room": "1000",
        "instructor": "",
        "status": "Closed",
        "additional_info": []
      }
    ]
  },
  {
    "department": "A A",
    "number": "498SPECIAL TOPIC",
    "title": "S",
    "sections": [
      {
        "sln": "",
        "section_id": "",
        "times": "",
        "building": "",
        "room": "",
        "instructor": "",
        "status": "",
        "additional_info": []
      },
      {
        "sln": "",
        "section_id": "",
        "times": "",
        "building": "",
        "room": "",
        "instructor": "",
        "status": "",
        "additional_info": []
      }
    ]
  },
  {
    "department": "A A",
    "number": "499UNDERGRAD RESEARC",
    "title": "H",
    "sections": [
      {
        "sln": "",
        "section_id": "",
        "times": "",
        "building": "",
        "room": "",
        "instructor": "",
        "status": "",
        "additional_info": []
      },
      {
        "sln": "",
        "section_id": "",
        "times": "",
        "building": "",
        "room": "",
        "instructor": "",
        "status": "",
        "additional_info": []
      }
    ]
  },
  {
    "department": "A A",
    "number": "507INCOMP FLUID",
    "title": "MECH",
    "sections": [
      {
        "sln": "",
        "section_id": "",
        "times": "",
        "building": "",
        "room": "",
        "instructor": "",
        "status": "Open",
        "additional_info": []
      }
    ]
  },
  {
    "department": "A A",
    "number": "516STAB",
    "title": "& CON FLT VEH",
    "sections": [
      {
        "sln": "",
        "section_id": "",
        "times": "",
        "building": "",
        "room": "",
        "instructor": "",
        "status": "Open",
        "additional_info": []
      }
    ]
  },
  {
    "department": "A A",
    "number": "540FINITE ELM",
    "title": "ANLYS I",
    "sections": [
      {
        "sln": "",
        "section_id": "",
        "times": "",
        "building": "WF",
        "room": "830",
        "instructor": "",
        "status": "Closed",
        "additional_info": []
      }
    ]
  },
  {
    "department": "A A",
    "number": "543COMPRESSIBLE CF",
    "title": "D",
    "sections": [
      {
        "sln": "",
        "section_id": "",
        "times": "",
        "building": "WF",
        "room": "1000",
        "instructor": "",
        "status": "Open",
        "additional_info": []
      }
    ]
  },
  {
    "department": "A A",
    "number": "547LINEAR SYSTEM",
    "title": "S",
    "sections": [
      {
        "sln": "",
        "section_id": "",
        "times": "",
        "building": "",
        "room": "",
        "instructor": "",
        "status": "Open",
        "additional_info": []
      }
    ]
  },
  {
    "department": "A A",
    "number": "557PHYS FUSION",
    "title": "PLASMAS",
    "sections": [
      {
        "sln": "",
        "section_id": "",
        "times": "",
        "building": "WF",
        "room": "1130",
        "instructor": "",
        "status": "Open",
        "additional_info": []
      }
    ]
  },
  {
    "department": "A A",
    "number": "559PLASMA SCIENCE",
    "title": "SMNR",
    "sections": [
      {
        "sln": "",
        "section_id": "",
        "times": "",
        "building": "",
        "room": "",
        "instructor": "",
        "status": "Open",
        "additional_info": []
      }
    ]
  },
  {
    "department": "A A",
    "number": "578CONVEX OPTIMIZATIO",
    "title": "N",
    "sections": [
      {
        "sln": "",
        "section_id": "",
        "times": "",
        "building": "MWF",
        "room": "1130",
        "instructor": "",
        "status": "Open",
        "additional_info": []
      }
    ]
  },
  {
    "department": "A A",
    "number": "594ROBUST CONTRO",
    "title": "L",
    "sections": [
      {
        "sln": "",
        "section_id": "",
        "times": "",
        "building": "",
        "room": "",
        "instructor": "",
        "status": "Open",
        "additional_info": []
      }
    ]
  },
  {
    "department": "A A",
    "number": "598SPECIAL TOPIC",
    "title": "S",
    "sections": [
      {
        "sln": "",
        "section_id": "",
        "times": "",
        "building": "WF",
        "room": "130",
        "instructor": "",
        "status": "Open",
        "additional_info": []
      },
      {
        "sln": "",
        "section_id": "",
        "times": "",
        "building": "WF",
        "room": "830",
        "instructor": "",
        "status": "",
        "additional_info": []
      },
      {
        "sln": "",
        "section_id": "",
        "times": "",
        "building": "WF",
        "room": "100",
        "instructor": "",
        "status": "",
        "additional_info": []
      },
      {
        "sln": "",
        "section_id": "",
        "times": "",
        "building": "WF",
        "room": "100",
        "instructor": "",
        "status": "",
        "additional_info": []
      }
    ]
  },
  {
    "department": "A A",
    "number": "599SPECIAL PROJECT",
    "title": "S",
    "sections": [
      {
        "sln": "",
        "section_id": "",
        "times": "",
        "building": "",
        "room": "",
        "instructor": "",
        "status": "",
        "additional_info": []
      },
      {
        "sln": "",
        "section_id": "",
        "times": "",
        "building": "",
        "room": "",
        "instructor": "",
        "status": "",
        "additional_info": []
      }
    ]
  },
  {
    "department": "A A",
    "number": "600INDEPNDNT STDY",
    "title": "/RSCH",
    "sections": [
      {
        "sln": "",
        "section_id": "",
        "times": "",
        "building": "",
        "room": "",
        "instructor": "",
        "status": "",
        "additional_info": []
      }
    ]
  },
  {
    "department": "A A",
    "number": "700MASTERS THESI",
    "title": "S",
    "sections": [
      {
        "sln": "",
        "section_id": "",
        "times": "",
        "building": "",
        "room": "",
        "instructor": "",
        "status": "",
        "additional_info": []
      }
    ]
  },
  {
    "department": "A A",
    "number": "800DOCTORAL DISSERTAT",
    "title": "N",
    "sections": [
      {
        "sln": "",
        "section_id": "",
        "times": "",
        "building": "",
        "room": "",
        "instructor": "",
        "status": "",
        "additional_info": []
      }
    ]
  }
]