[
  {
    "department": "R E",
    "number": "250INTRO REAL",
    "title": "ESTATE",
    "sections": [
      {
        "sln": "",
        "section_id": "",
        "times": "",
        "building": "AT",
        "room": "50",
        "instructor": "",
        "status": "Open",
        "additional_info": []
      },
      {
        "sln": "",
        "section_id": "",
        "times": "MW     1030-1150",
        "building": "MW",
        "room": "1030",
        "instructor": "",
        "status": "Open",
        "additional_info": []
      },
      {
        "sln": "",
        "section_id": "",
        "times": "",
        "building": "",
        "room": "",
        "instructor": "",
        "status": "",
        "additional_info": []
      }
    ]
  },
  {
    "department": "R E",
    "number": "361PROP TRANSACTION",
    "title": "S",
    "sections": [
      {
        "sln": "",
        "section_id": "",
        "times": "",
        "building": "MW",
        "room": "200",
        "instructor": "",
        "status": "Open",
        "additional_info": []
      }
    ]
  },
  {
    "department": "R E",
    "number": "363RE DEVELOPMEN",
    "title": "T",
    "sections": [
      {
        "sln": "",
        "section_id": "",
        "times": "",
        "building": "MW",
        "room": "130",
        "instructor": "",
        "status": "Open",
        "additional_info": []
      },
      {
        "sln": "",
        "section_id": "",
        "times": "",
        "building": "CAP",
        "room": "35PREREQS",
        "instructor": "ENFORCED",
        "status": "Open",
        "additional_info": []
      }
    ]
  },
  {
    "department": "R E",
    "number": "397INTRO RE",
    "title": "DATA MODEL",
    "sections": [
      {
        "sln": "",
        "section_id": "",
        "times": "",
        "building": "CAP",
        "room": "100PREREQS",
        "instructor": "ENFORCEDRESTRICTED TO MAJORS PERIOD I",
        "status": "Open",
        "additional_info": []
      },
      {
        "sln": "",
        "section_id": "",
        "times": "",
        "building": "CAP",
        "room": "30PREREQS",
        "instructor": "ENFORCED",
        "status": "Open",
        "additional_info": []
      },
      {
        "sln": "",
        "section_id": "",
        "times": "",
        "building": "CAP",
        "room": "35PREREQS",
        "instructor": "ENFORCED",
        "status": "Open",
        "additional_info": []
      },
      {
        "sln": "",
        "section_id": "",
        "times": "",
        "building": "CAP",
        "room": "35PREREQS",
        "instructor": "ENFORCED",
        "status": "Open",
        "additional_info": []
      }
    ]
  },
  {
    "department": "R E",
    "number": "400ACCOUNTING FOR",
    "title": "RE",
    "sections": [
      {
        "sln": "",
        "section_id": "",
        "times": "MW     400-520",
        "building": "MW",
        "room": "400",
        "instructor": "",
        "status": "Open",
        "additional_info": []
      }
    ]
  },
  {
    "department": "R E",
    "number": "401HOUSING POLIC",
    "title": "Y",
    "sections": [
      {
        "sln": "",
        "section_id": "",
        "times": "",
        "building": "IS",
        "room": "40",
        "instructor": "",
        "status": "Open",
        "additional_info": []
      }
    ]
  },
  {
    "department": "R E",
    "number": "411RE APPRAISA",
    "title": "L",
    "sections": [
      {
        "sln": "",
        "section_id": "",
        "times": "",
        "building": "CAP",
        "room": "50RE",
        "instructor": "MAJORS ONLY PERIOD IPREREQS ENFORCED",
        "status": "Open",
        "additional_info": []
      }
    ]
  },
  {
    "department": "R E",
    "number": "413RE FINANCE",
    "title": "INVEST",
    "sections": [
      {
        "sln": "",
        "section_id": "",
        "times": "",
        "building": "IS",
        "room": "40PREREQS",
        "instructor": "ENFORCED",
        "status": "Open",
        "additional_info": []
      }
    ]
  },
  {
    "department": "R E",
    "number": "416RE MARKET",
    "title": "ANALYSIS",
    "sections": [
      {
        "sln": "",
        "section_id": "",
        "times": "",
        "building": "MW",
        "room": "1000",
        "instructor": "",
        "status": "Open",
        "additional_info": []
      },
      {
        "sln": "",
        "section_id": "",
        "times": "",
        "building": "AT",
        "room": "50PREREQS",
        "instructor": "ENFORCED",
        "status": "Open",
        "additional_info": []
      }
    ]
  },
  {
    "department": "R E",
    "number": "462RES DATA",
    "title": "ANALYTICS",
    "sections": [
      {
        "sln": "",
        "section_id": "",
        "times": "MW     1100-120",
        "building": "MW",
        "room": "1100",
        "instructor": "",
        "status": "",
        "additional_info": []
      }
    ]
  },
  {
    "department": "R E",
    "number": "464AFFORDABLE HOUSIN",
    "title": "G",
    "sections": [
      {
        "sln": "",
        "section_id": "",
        "times": "MW     830-1020",
        "building": "MW",
        "room": "830",
        "instructor": "",
        "status": "",
        "additional_info": []
      }
    ]
  },
  {
    "department": "R E",
    "number": "480PROFESSIONAL DEVP",
    "title": "T",
    "sections": [
      {
        "sln": "",
        "section_id": "",
        "times": "",
        "building": "AT",
        "room": "60RE",
        "instructor": "MAJORS ONLY PERIOD I",
        "status": "Open",
        "additional_info": []
      }
    ]
  },
  {
    "department": "R E",
    "number": "490INDEPENDENT STUD",
    "title": "Y",
    "sections": [
      {
        "sln": "",
        "section_id": "",
        "times": "",
        "building": "",
        "room": "",
        "instructor": "",
        "status": "Closed",
        "additional_info": []
      }
    ]
  },
  {
    "department": "R E",
    "number": "510INTRO REAL",
    "title": "ESTATE",
    "sections": [
      {
        "sln": "",
        "section_id": "",
        "times": "",
        "building": "",
        "room": "",
        "instructor": "",
        "status": "",
        "additional_info": []
      }
    ]
  },
  {
    "department": "R E",
    "number": "513RE FINANCE",
    "title": "INVEST",
    "sections": [
      {
        "sln": "",
        "section_id": "",
        "times": "",
        "building": "",
        "room": "",
        "instructor": "",
        "status": "",
        "additional_info": []
      }
    ]
  },
  {
    "department": "R E",
    "number": "514NEGOTATIONS B",
    "title": "E",
    "sections": [
      {
        "sln": "",
        "section_id": "",
        "times": "",
        "building": "",
        "room": "",
        "instructor": "",
        "status": "",
        "additional_info": []
      }
    ]
  },
  {
    "department": "R E",
    "number": "515REAL ESTATE",
    "title": "LAW",
    "sections": [
      {
        "sln": "",
        "section_id": "",
        "times": "",
        "building": "",
        "room": "",
        "instructor": "",
        "status": "",
        "additional_info": []
      }
    ]
  },
  {
    "department": "R E",
    "number": "540ADV RE",
    "title": "FINANCE & INV",
    "sections": [
      {
        "sln": "",
        "section_id": "",
        "times": "",
        "building": "",
        "room": "",
        "instructor": "",
        "status": "",
        "additional_info": []
      }
    ]
  },
  {
    "department": "R E",
    "number": "541R E",
    "title": "CAPITAL MARKETS",
    "sections": [
      {
        "sln": "",
        "section_id": "",
        "times": "",
        "building": "",
        "room": "",
        "instructor": "",
        "status": "",
        "additional_info": []
      }
    ]
  },
  {
    "department": "R E",
    "number": "552RE CAREER",
    "title": "DEVEL",
    "sections": [
      {
        "sln": "",
        "section_id": "",
        "times": "",
        "building": "MW",
        "room": "1030",
        "instructor": "",
        "status": "",
        "additional_info": []
      }
    ]
  },
  {
    "department": "R E",
    "number": "562RES DATA",
    "title": "ANALYTICS",
    "sections": [
      {
        "sln": "",
        "section_id": "",
        "times": "MW     1100-120",
        "building": "MW",
        "room": "1100",
        "instructor": "",
        "status": "",
        "additional_info": []
      }
    ]
  },
  {
    "department": "R E",
    "number": "563HOUSING MARKET",
    "title": "S",
    "sections": [
      {
        "sln": "",
        "section_id": "",
        "times": "",
        "building": "",
        "room": "",
        "instructor": "",
        "status": "",
        "additional_info": []
      }
    ]
  },
  {
    "department": "R E",
    "number": "564AFFORDABLE HOUSIN",
    "title": "G",
    "sections": [
      {
        "sln": "",
        "section_id": "",
        "times": "MW     830-1020",
        "building": "MW",
        "room": "830",
        "instructor": "",
        "status": "",
        "additional_info": []
      }
    ]
  },
  {
    "department": "R E",
    "number": "600INDEPNDNT STDY",
    "title": "/RSCH",
    "sections": [
      {
        "sln": "",
        "section_id": "",
        "times": "",
        "building": "",
        "room": "",
        "instructor": "",
        "status": "Open",
        "additional_info": []
      }
    ]
  }
]